<?xml version="1.0" encoding="UTF-8"?>
<package xmlns="http://expath.org/ns/pkg" name="${package-name}" abbrev="${package-abbrev}" version="${project.version}"
    spec="1.0">
    <title>${package-title}</title>
    <author id="exist-db">Stephan Makowski</author>
    <website>${project.url}</website>
    <license>GNU General Public License, version 1</license>
    <copyright>true</copyright>
    <type>library</type>
    <status>stable</status>
    <tag>${project.artifactId}</tag>
    <tag>library</tag>
    <tag>additional features</tag>
    <category id="libs">Libraries</category>
    <category id="exist">eXist extensions</category>
    <dependency processor="http://exist-db.org" semver-min="3.0.4" />
    <dependencySets>
        <dependencySet>
            <groupId>${project.groupId}</groupId>
            <artifactId>${project.artifactId}</artifactId>
            <version>${project.version}</version>
        </dependencySet>
        <dependencySet>
            <groupId>com.bmsi</groupId>
            <artifactId>gnudiff</artifactId>
            <version>${gnudiff.version}</version>
        </dependencySet>
    </dependencySets>
    <components>
        <resource>
            <public-uri>${additional.module.namespace}</public-uri>
            <file>${additional.module.java.package}.${additional.module.java.classname}</file>
        </resource>
    </components><!--
    <xquerySets>
        <xquerySet>
            <namespace>http://itineranova.be/additional</namespace>
            <directory>./src</directory>
            <outputDirectory>content</outputDirectory>
        </xquerySet>
    </xquerySets> -->
</package>
